giraumon/__about__.py
giraumon/__init__.py
giraumon/cli.py
giraumon/initialize.py
giraumon/utility.py
giraumon/tests/__init__.py
giraumon/tests/test_cli.py
giraumon/tests/test_initialize.py
giraumon/tests/test_utility.py
giraumon-0.0.1.dist-info/DESCRIPTION.rst
giraumon-0.0.1.dist-info/METADATA
giraumon-0.0.1.dist-info/RECORD
giraumon-0.0.1.dist-info/WHEEL
giraumon-0.0.1.dist-info/entry_points.txt
giraumon-0.0.1.dist-info/metadata.json
giraumon-0.0.1.dist-info/top_level.txt
