Metadata-Version: 2.0
Name: giraumon
Version: 0.0.1
Summary: Tools for developer to manage Mirounga Hosting Service
Home-page: https://github.com/mgasystem/giraumon
Author: Mirounga Team
Author-email: info@mirounga.net
License: GPLv3
Keywords: hosting development
Platform: UNKNOWN
Classifier: Development Status :: 3 - Alpha
Classifier: Intended Audience :: Developers
Classifier: Topic :: Software Development :: Build Tools
Classifier: License :: OSI Approved :: MIT License
Classifier: Programming Language :: Python :: 2
Classifier: Programming Language :: Python :: 2.7
Classifier: Programming Language :: Python :: 3
Classifier: Programming Language :: Python :: 3.3
Classifier: Programming Language :: Python :: 3.4
Classifier: Programming Language :: Python :: 3.5
Requires-Dist: click (==6.7)
Requires-Dist: GitPython (==2.1.5)
